pagination/__init__.py
pagination/templatetags/__init__.py
pagination/templatetags/querystrings.py
pagination/tests/__init__.py
pagination/tests/test_querystrings.py
pagination/tests/factories.py
pagination/tests/utils.py
pagination/templates/includes/_pagination.html
incuna_pagination-0.1.3.dist-info/WHEEL
incuna_pagination-0.1.3.dist-info/RECORD
incuna_pagination-0.1.3.dist-info/METADATA
incuna_pagination-0.1.3.dist-info/metadata.json
incuna_pagination-0.1.3.dist-info/DESCRIPTION.rst
incuna_pagination-0.1.3.dist-info/top_level.txt
